{
  "id": "rc_75_pin_retries",
  "name": "RC 75 — Allowable PIN Tries Exceeded",
  "description": "Card blocked after too many incorrect PIN attempts. Triggers RC 75.",
  "event_type": "authorization",
  "request": {
    "transaction_id": "TXN_RC75_001",
    "pan": "4111111111111111",
    "amount": 2000,
    "currency": "840",
    "mcc": "6011",
    "merchant_name": "Bank ATM",
    "merchant_city": "Denver",
    "merchant_state": "CO",
    "merchant_country": "USA",
    "pos_entry_mode": "021",
    "terminal_id": "ATM0075",
    "acquiring_institution_id": "123456",
    "forwarding_institution_id": "123456"
  },
  "expected_network_response_code": "05",
  "expected_customer_decision": "DECLINED",
  "tags": ["rc_coverage", "decline", "pin_retries"]
}
